pluto_python/__init__.py
pluto_python/calculator.py
pluto_python/mhd_jet.py
pluto_python/pluto.py
pluto_python/spacetime.py
pluto_python/tools.py
pluto_python-0.0.5.dist-info/LICENSE
pluto_python-0.0.5.dist-info/METADATA
pluto_python-0.0.5.dist-info/WHEEL
pluto_python-0.0.5.dist-info/top_level.txt
pluto_python-0.0.5.dist-info/RECORD
