Metadata-Version: 2.1
Name: pluto_python
Version: 0.0.5
Summary: Package includes analytical code to read in HDF5 output files from PLUTO
Home-page: https://github.com/mateczentye/pluto_python
Author: Mate Czentye
Author-email: czentyemate@gmail.com
License: MIT
Platform: UNKNOWN
License-File: LICENSE
